pytest_subprocess/__init__.py
pytest_subprocess/asyncio_subprocess.py
pytest_subprocess/exceptions.py
pytest_subprocess/fake_popen.py
pytest_subprocess/fake_process.py
pytest_subprocess/fixtures.py
pytest_subprocess/process_dispatcher.py
pytest_subprocess/process_recorder.py
pytest_subprocess/py.typed
pytest_subprocess/types.py
pytest_subprocess/utils.py
pytest_subprocess-1.5.2.dist-info/LICENSE
pytest_subprocess-1.5.2.dist-info/METADATA
pytest_subprocess-1.5.2.dist-info/WHEEL
pytest_subprocess-1.5.2.dist-info/entry_points.txt
pytest_subprocess-1.5.2.dist-info/top_level.txt
pytest_subprocess-1.5.2.dist-info/RECORD
