Metadata-Version: 2.1
Name: pytest-subprocess
Version: 1.5.2
Summary: A plugin to fake subprocess for pytest
Author: Andrzej Klajnert
Author-email: python@aklajnert.pl
Maintainer: Andrzej Klajnert
Maintainer-email: python@aklajnert.pl
License: MIT
Project-URL: Documentation, https://pytest-subprocess.readthedocs.io
Project-URL: Source, https://github.com/aklajnert/pytest-subprocess
Project-URL: Tracker, https://github.com/aklajnert/pytest-subprocess/issues
Classifier: Development Status :: 5 - Production/Stable
Classifier: Framework :: Pytest
Classifier: Intended Audience :: Developers
Classifier: Topic :: Software Development :: Testing
Classifier: Programming Language :: Python
Classifier: Programming Language :: Python :: 3
Classifier: Programming Language :: Python :: 3.6
Classifier: Programming Language :: Python :: 3.7
Classifier: Programming Language :: Python :: 3.8
Classifier: Programming Language :: Python :: 3.9
Classifier: Programming Language :: Python :: 3.10
Classifier: Programming Language :: Python :: 3.11
Classifier: Programming Language :: Python :: Implementation :: CPython
Classifier: Programming Language :: Python :: Implementation :: PyPy
Classifier: Operating System :: OS Independent
Classifier: License :: OSI Approved :: MIT License
Requires-Python: >=3.6
License-File: LICENSE
Requires-Dist: pytest >=4.0.0
Provides-Extra: dev
Requires-Dist: nox ; extra == 'dev'
Requires-Dist: changelogd ; extra == 'dev'
Provides-Extra: docs
Requires-Dist: sphinx ; extra == 'docs'
Requires-Dist: furo ; extra == 'docs'
Requires-Dist: sphinxcontrib-napoleon ; extra == 'docs'
Requires-Dist: sphinx-autodoc-typehints ; extra == 'docs'
Requires-Dist: changelogd ; extra == 'docs'
Provides-Extra: test
Requires-Dist: pytest >=4.0 ; extra == 'test'
Requires-Dist: coverage ; extra == 'test'
Requires-Dist: docutils >=0.12 ; extra == 'test'
Requires-Dist: Pygments >=2.0 ; extra == 'test'
Requires-Dist: pytest-rerunfailures ; extra == 'test'
Requires-Dist: pytest-asyncio >=0.15.1 ; extra == 'test'
Requires-Dist: pytest-timeout ; extra == 'test'
Requires-Dist: anyio ; extra == 'test'
